odoo/addons/sale_product_variant_attribute_tax/README.rst
odoo/addons/sale_product_variant_attribute_tax/__init__.py
odoo/addons/sale_product_variant_attribute_tax/__manifest__.py
odoo/addons/sale_product_variant_attribute_tax/i18n/es.po
odoo/addons/sale_product_variant_attribute_tax/i18n/es_AR.po
odoo/addons/sale_product_variant_attribute_tax/i18n/it.po
odoo/addons/sale_product_variant_attribute_tax/i18n/sale_product_variant_attribute_tax.pot
odoo/addons/sale_product_variant_attribute_tax/models/__init__.py
odoo/addons/sale_product_variant_attribute_tax/models/sale_order.py
odoo/addons/sale_product_variant_attribute_tax/readme/CONTRIBUTORS.rst
odoo/addons/sale_product_variant_attribute_tax/readme/DESCRIPTION.rst
odoo/addons/sale_product_variant_attribute_tax/readme/USAGE.rst
odoo/addons/sale_product_variant_attribute_tax/static/description/icon.png
odoo/addons/sale_product_variant_attribute_tax/static/description/index.html
odoo/addons/sale_product_variant_attribute_tax/tests/__init__.py
odoo/addons/sale_product_variant_attribute_tax/tests/test_sale_product_variant_attribute_tax.py
odoo13_addon_sale_product_variant_attribute_tax-13.0.1.0.1.dev10.dist-info/METADATA
odoo13_addon_sale_product_variant_attribute_tax-13.0.1.0.1.dev10.dist-info/WHEEL
odoo13_addon_sale_product_variant_attribute_tax-13.0.1.0.1.dev10.dist-info/top_level.txt
odoo13_addon_sale_product_variant_attribute_tax-13.0.1.0.1.dev10.dist-info/RECORD
