Metadata-Version: 2.1
Name: odoo13-addon-sale-product-variant-attribute-tax
Version: 13.0.1.0.1.dev10
Summary: Bring the taxes associated to product values
Home-page: https://github.com/OCA/product-variant
Author: Tecnativa, Odoo Community Association (OCA)
Author-email: support@odoo-community.org
License: AGPL-3
Platform: UNKNOWN
Classifier: Programming Language :: Python
Classifier: Framework :: Odoo
Classifier: Framework :: Odoo :: 13.0
Classifier: License :: OSI Approved :: GNU Affero General Public License v3
Classifier: Development Status :: 5 - Production/Stable
Requires-Python: >=3.5
Requires-Dist: odoo13-addon-product-variant-attribute-tax
Requires-Dist: odoo13-addon-sale-variant-configurator
Requires-Dist: odoo <13.1dev,>=13.0a
